spvideoutils/__init__.py
spvideoutils/camera.py
spvideoutils/utils.py
spvideoutils/video.py
spvideoutils/video_capture.py
spvideoutils/video_crop.py
spvideoutils/video_merge.py
spvideoutils/video_split.py
spvideoutils-0.0.3.dist-info/LICENSE.txt
spvideoutils-0.0.3.dist-info/METADATA
spvideoutils-0.0.3.dist-info/WHEEL
spvideoutils-0.0.3.dist-info/entry_points.txt
spvideoutils-0.0.3.dist-info/top_level.txt
spvideoutils-0.0.3.dist-info/RECORD
