Metadata-Version: 2.1
Name: spvideoutils
Version: 0.0.3
Summary: Scripts for saving and splitting video files for other projects
Home-page: https://github.com/sanjeevs/spvideoutils
Author: Sanjeev Singh
Author-email: snjvsingh123@gmail.com
License: UNKNOWN
Platform: UNKNOWN
Classifier: Programming Language :: Python :: 3
Classifier: Programming Language :: Python :: 3.6
Classifier: Programming Language :: Python :: 3.7
Classifier: License :: OSI Approved :: MIT License
Classifier: Operating System :: OS Independent
Classifier: Development Status :: 3 - Alpha
License-File: LICENSE.txt
Requires-Dist: opencv-python
Provides-Extra: dev
Requires-Dist: pytest (>=3.7) ; extra == 'dev'
Requires-Dist: check-manifest ; extra == 'dev'
Requires-Dist: twine ; extra == 'dev'
